{
    "billing.bundle.js": "/assets/frappe/dist/js/billing.bundle.CPRCUCBA.js",
    "bootstrap-4-web.bundle.js": "/assets/frappe/dist/js/bootstrap-4-web.bundle.AZ67VXZX.js",
    "controls.bundle.js": "/assets/frappe/dist/js/controls.bundle.C246K7DR.js",
    "data_import_tools.bundle.js": "/assets/frappe/dist/js/data_import_tools.bundle.RPIHPPDY.js",
    "desk.bundle.js": "/assets/frappe/dist/js/desk.bundle.DPJBEEOA.js",
    "dialog.bundle.js": "/assets/frappe/dist/js/dialog.bundle.KM2KJGRI.js",
    "form.bundle.js": "/assets/frappe/dist/js/form.bundle.XIHVQM2S.js",
    "frappe-web.bundle.js": "/assets/frappe/dist/js/frappe-web.bundle.EDDMKXGE.js",
    "libs.bundle.js": "/assets/frappe/dist/js/libs.bundle.LLRFRX7M.js",
    "list.bundle.js": "/assets/frappe/dist/js/list.bundle.NKDNFJLP.js",
    "logtypes.bundle.js": "/assets/frappe/dist/js/logtypes.bundle.MJKW7EK3.js",
    "onboarding_tours.bundle.js": "/assets/frappe/dist/js/onboarding_tours.bundle.P7QYMXLW.js",
    "report.bundle.js": "/assets/frappe/dist/js/report.bundle.KCA65RR6.js",
    "sentry.bundle.js": "/assets/frappe/dist/js/sentry.bundle.SI3DB3BY.js",
    "telemetry.bundle.js": "/assets/frappe/dist/js/telemetry.bundle.DQEBDMFO.js",
    "user_profile_controller.bundle.js": "/assets/frappe/dist/js/user_profile_controller.bundle.TAMQL3L3.js",
    "video_player.bundle.js": "/assets/frappe/dist/js/video_player.bundle.IOEIXC2G.js",
    "web_form.bundle.js": "/assets/frappe/dist/js/web_form.bundle.ECVLDM6O.js",
    "form_builder.bundle.js": "/assets/frappe/dist/js/form_builder.bundle.BTYJAWE7.js",
    "print_format_builder.bundle.js": "/assets/frappe/dist/js/print_format_builder.bundle.G5X2D5LJ.js",
    "workflow_builder.bundle.js": "/assets/frappe/dist/js/workflow_builder.bundle.6WQ3NY27.js",
    "build_events.bundle.js": "/assets/frappe/dist/js/build_events.bundle.QC4YLK6J.js",
    "file_uploader.bundle.js": "/assets/frappe/dist/js/file_uploader.bundle.YZWGRP5O.js",
    "kanban_board.bundle.js": "/assets/frappe/dist/js/kanban_board.bundle.OUFA2R27.js",
    "desk.bundle.css": "/assets/frappe/dist/css/desk.bundle.HKFVVCCC.css",
    "email.bundle.css": "/assets/frappe/dist/css/email.bundle.UWS5XFX5.css",
    "login.bundle.css": "/assets/frappe/dist/css/login.bundle.EQ6XAPE7.css",
    "print.bundle.css": "/assets/frappe/dist/css/print.bundle.B2ETNXU2.css",
    "print_format.bundle.css": "/assets/frappe/dist/css/print_format.bundle.4GMYUN5C.css",
    "report.bundle.css": "/assets/frappe/dist/css/report.bundle.NYSPSZW3.css",
    "web_form.bundle.css": "/assets/frappe/dist/css/web_form.bundle.EZNJ75OL.css",
    "website.bundle.css": "/assets/frappe/dist/css/website.bundle.MTEXFHPY.css",
    "bank-reconciliation-tool.bundle.js": "/assets/erpnext/dist/js/bank-reconciliation-tool.bundle.SSX4GOM5.js",
    "erpnext-web.bundle.js": "/assets/erpnext/dist/js/erpnext-web.bundle.253I7LT4.js",
    "erpnext.bundle.js": "/assets/erpnext/dist/js/erpnext.bundle.SFJQ6AGH.js",
    "item-dashboard.bundle.js": "/assets/erpnext/dist/js/item-dashboard.bundle.5CVRP76B.js",
    "point-of-sale.bundle.js": "/assets/erpnext/dist/js/point-of-sale.bundle.IOF5ACZK.js",
    "bom_configurator.bundle.js": "/assets/erpnext/dist/js/bom_configurator.bundle.6NZSNVVE.js",
    "erpnext-web.bundle.css": "/assets/erpnext/dist/css/erpnext-web.bundle.C2SFDDMX.css",
    "erpnext.bundle.css": "/assets/erpnext/dist/css/erpnext.bundle.GHBG4C7Z.css",
    "erpnext_email.bundle.css": "/assets/erpnext/dist/css/erpnext_email.bundle.Y2HZJBQS.css",
    "hierarchy-chart.bundle.js": "/assets/hrms/dist/js/hierarchy-chart.bundle.IUKCUWNT.js",
    "hrms.bundle.js": "/assets/hrms/dist/js/hrms.bundle.VDZJREXR.js",
    "interview.bundle.js": "/assets/hrms/dist/js/interview.bundle.7RFUFZ4X.js",
    "performance.bundle.js": "/assets/hrms/dist/js/performance.bundle.Q4BFJ4IS.js",
    "hrms.bundle.css": "/assets/hrms/dist/css/hrms.bundle.QFALUXUH.css"
}